CHANGES.txt
LICENSE.txt
MANIFEST.in
README.md
pyproject.toml
setup.cfg
setup.py
tox.ini
src/imports_logger/__init__.py
src/imports_logger.egg-info/PKG-INFO
src/imports_logger.egg-info/SOURCES.txt
src/imports_logger.egg-info/dependency_links.txt
src/imports_logger.egg-info/not-zip-safe
src/imports_logger.egg-info/requires.txt
src/imports_logger.egg-info/top_level.txt
tests/__init__.py
tests/test_core.py