Metadata-Version: 2.1
Name: imports-logger
Version: 1.0.1
Summary: Quick tool to log import statements
Home-page: https://github.com/jvanasco/imports_logger
Author: Jonathan Vanasco
Author-email: jonathan@findmeon.com
License: MIT
Keywords: import logging memory
Platform: UNKNOWN
Classifier: Intended Audience :: Developers
Classifier: Programming Language :: Python :: 2
Classifier: Programming Language :: Python :: 3
Classifier: License :: OSI Approved :: MIT License
Provides-Extra: testing
